LICENSE
README.md
pyproject.toml
setup.cfg
setup.py
offline_evaluation.egg-info/PKG-INFO
offline_evaluation.egg-info/SOURCES.txt
offline_evaluation.egg-info/dependency_links.txt
offline_evaluation.egg-info/requires.txt
offline_evaluation.egg-info/top_level.txt
ope/__init__.py
ope/estimators/__init__.py
ope/estimators/gbdt.py
ope/estimators/linear.py
ope/methods/__init__.py
ope/methods/direct_method.py
ope/methods/doubly_robust.py
ope/methods/inverse_propensity_scoring.py
ope/training/__init__.py
ope/training/predictor.py
ope/utils/__init__.py
ope/utils/stats.py