Metadata-Version: 2.1
Name: offline-evaluation
Version: 0.0.6
Summary: Implementations of common offline policy evaluation methods.
Home-page: https://github.com/banditml/offline-policy-evaluation
Author: Edoardo Conti, Lionel Vital, Joseph Gilley
Author-email: team@banditml.com
License: UNKNOWN
Platform: UNKNOWN
Classifier: Programming Language :: Python :: 3
Classifier: License :: OSI Approved :: GNU General Public License (GPL)
Classifier: Operating System :: OS Independent
Requires-Python: >=3.6
